claudebox/__init__.py
claudebox/box.py
claudebox/exceptions.py
claudebox/logging.py
claudebox/results.py
claudebox/rewards.py
claudebox/security.py
claudebox/session.py
claudebox/skill_loader.py
claudebox/skills.py
claudebox/templates.py
claudebox/tools.py
claudebox/trajectory.py
claudebox/workspace.py
claudebox-0.3.1.dist-info/METADATA
claudebox-0.3.1.dist-info/WHEEL
claudebox-0.3.1.dist-info/licenses/LICENSE
claudebox-0.3.1.dist-info/RECORD
