Metadata-Version: 2.4
Name: claudebox
Version: 0.3.1
Summary: Run Claude Code CLI in isolated micro-VMs with persistent workspaces
Project-URL: Homepage, https://github.com/boxlite-labs/claudebox
Project-URL: Repository, https://github.com/boxlite-labs/claudebox
Project-URL: Issues, https://github.com/boxlite-labs/claudebox/issues
Author: BoxLite Labs
License-Expression: MIT
License-File: LICENSE
Keywords: agent,ai,anthropic,claude,isolation,sandbox,vm
Classifier: Development Status :: 3 - Alpha
Classifier: Intended Audience :: Developers
Classifier: License :: OSI Approved :: MIT License
Classifier: Programming Language :: Python :: 3
Classifier: Programming Language :: Python :: 3.10
Classifier: Programming Language :: Python :: 3.11
Classifier: Programming Language :: Python :: 3.12
Classifier: Programming Language :: Python :: 3.13
Classifier: Programming Language :: Python :: 3.14
Classifier: Topic :: Scientific/Engineering :: Artificial Intelligence
Classifier: Topic :: Software Development :: Libraries :: Python Modules
Requires-Python: >=3.10
Requires-Dist: boxlite>=0.4.4
Provides-Extra: dev
Requires-Dist: pytest-asyncio>=0.21; extra == 'dev'
Requires-Dist: pytest>=7.0; extra == 'dev'
Requires-Dist: ruff>=0.1.0; extra == 'dev'
